{"data":{"ABE#942":{"getConnectCode":{"user":{"displayName":"abe froman","connectCode":{"code":"ABE#942"},"rankedNetplayProfile":{"id":"0x35a290","ratingOrdinal":1877.554388,"ratingUpdateCount":273,"wins":141,"losses":132,"dailyGlobalPlacement":null,"dailyRegionalPlacement":null,"continent":"NORTH_AMERICA","characters":[{"id":"0x1aa1b8a","character":"MARTH","gameCount":2},{"id":"0x1aa1b8b","character":"FOX","gameCount":428},{"id":"0x1aa1b8c","character":"SHEIK","gameCount":2},{"id":"0x1aa1b8d","character":"FALCO","gameCount":85},{"id":"0x1aa1b8e","character":"DR_MARIO","gameCount":9},{"id":"0x1aa1b8f","character":"CAPTAIN_FALCON","gameCount":31}]}}},"tag":"feras"},"ACAB#466":{"getConnectCode":{"user":{"displayName":"white skerzo","connectCode":{"code":"ACAB#466"},"rankedNetplayProfile":{"id":"0x23c9b6","ratingOrdinal":1766.467039,"ratingUpdateCount":64,"wins":38,"losses":26,"dailyGlobalPlacement":null,"dailyRegionalPlacement":null,"continent":"NORTH_AMERICA","characters":[{"id":"0x23d488","character":"FOX","gameCount":145},{"id":"0x25172f","character":"SHEIK","gameCount":3},{"id":"0x41a3ab","character":"DONKEY_KONG","gameCount":2}]}}},"tag":"surskim"},"AJAX#727":{"getConnectCode":{"user":{"displayName":"Ajax23","connectCode":{"code":"AJAX#727"},"rankedNetplayProfile":{"id":"0xc83b99","ratingOrdinal":1100,"ratingUpdateCount":0,"wins":null,"losses":null,"dailyGlobalPlacement":null,"dailyRegionalPlacement":null,"continent":null,"characters":[]}}},"tag":""},"ANDY#941":{"getConnectCode":{"user":{"displayName":"zugzwang","connectCode":{"code":"ANDY#941"},"rankedNetplayProfile":{"id":"0x25f96f","ratingOrdinal":1680.921638,"ratingUpdateCount":101,"wins":51,"losses":50,"dailyGlobalPlacement":null,"dailyRegionalPlacement":null,"continent":"NORTH_AMERICA","characters":[{"id":"0x1a1f6d6","character":"SHEIK","gameCount":67},{"id":"0x1a1f6d7","character":"BOWSER","gameCount":6},{"id":"0x1a1f6d8","character":"FALCO","gameCount":71},{"id":"0x1a1f6d9","character":"FOX","gameCount":55},{"id":"0x1a1f6da","character":"CAPTAIN_FALCON","gameCount":3},{"id":"0x1a1f6db","character":"MARTH","gameCount":1},{"id":"0x1a1f6dc","character":"YOSHI","gameCount":33}]}}},"tag":"SpaceAndy"},"AZZU#900":{"getConnectCode":{"user":{"displayName":"wavedash","connectCode":{"code":"AZZU#900"},"rankedNetplayProfile":{"id":"0x256c80","ratingOrdinal":2018.673665,"ratingUpdateCount":23,"wins":17,"losses":6,"dailyGlobalPlacement":null,"dailyRegionalPlacement":null,"continent":"NORTH_AMERICA","characters":[{"id":"0x192b1b3","character":"FALCO","gameCount":49}]}}},"tag":""},"BIGS#164":{"getConnectCode":{"user":{"displayName":"BellaWthhybLoca","connectCode":{"code":"BIGS#164"},"rankedNetplayProfile":{"id":"0x25e707","ratingOrdinal":2189.107976,"ratingUpdateCount":390,"wins":207,"losses":183,"dailyGlobalPlacement":null,"dailyRegionalPlacement":null,"continent":"NORTH_AMERICA","characters":[{"id":"0x18660c4","character":"MARTH","gameCount":7},{"id":"0x18660c5","character":"SHEIK","gameCount":747}]}}},"tag":"Scooby"},"BIRD#324":{"getConnectCode":{"user":{"displayName":"everything else","connectCode":{"code":"BIRD#324"},"rankedNetplayProfile":{"id":"0x19d5f52","ratingOrdinal":1949.656214,"ratingUpdateCount":37,"wins":22,"losses":15,"dailyGlobalPlacement":null,"dailyRegionalPlacement":null,"continent":"NORTH_AMERICA","characters":[{"id":"0x19d62e2","character":"MARIO","gameCount":4},{"id":"0x19d66b8","character":"DR_MARIO","gameCount":6},{"id":"0x19d6afe","character":"LUIGI","gameCount":6},{"id":"0x19eac34","character":"GAME_AND_WATCH","gameCount":4},{"id":"0x19eaea2","character":"ZELDA","gameCount":3},{"id":"0x19eb1fb","character":"YOUNG_LINK","gameCount":1},{"id":"0x19eb1fc","character":"NESS","gameCount":1},{"id":"0x19eb1fd","character":"DONKEY_KONG","gameCount":6},{"id":"0x19f38b8","character":"MARTH","gameCount":8},{"id":"0x19f3b87","character":"SAMUS","gameCount":1},{"id":"0x19f3b88","character":"CAPTAIN_FALCON","gameCount":4},{"id":"0x19f3dc2","character":"JIGGLYPUFF","gameCount":4},{"id":"0x19f3f29","character":"FOX","gameCount":6},{"id":"0x19f41d4","character":"PIKACHU","gameCount":3},{"id":"0x19f44b6","character":"ICE_CLIMBERS","gameCount":5},{"id":"0x19f4c68","character":"SHEIK","gameCount":11},{"id":"0x19f502a","character":"PEACH","gameCount":8},{"id":"0x19f8f2a","character":"ROY","gameCount":1},{"id":"0x19f95f3","character":"KIRBY","gameCount":1},{"id":"0x19f95f4","character":"GANONDORF","gameCount":2},{"id":"0x19f9997","character":"LINK","gameCount":1}]}}},"tag":"thedarklord"},"BLU#873":{"getConnectCode":{"user":{"displayName":"ratio","connectCode":{"code":"BLU#873"},"rankedNetplayProfile":{"id":"0x23c722","ratingOrdinal":1523.308718,"ratingUpdateCount":413,"wins":205,"losses":208,"dailyGlobalPlacement":null,"dailyRegionalPlacement":null,"continent":"NORTH_AMERICA","characters":[{"id":"0x19a0d56","character":"FOX","gameCount":10},{"id":"0x19a0d57","character":"ZELDA","gameCount":7},{"id":"0x19a0d58","character":"PEACH","gameCount":2},{"id":"0x19a0d59","character":"MARTH","gameCount":4},{"id":"0x19a0d5a","character":"SHEIK","gameCount":697}]}}},"tag":"Quoise"},"BOB#579":{"getConnectCode":{"user":{"displayName":"Cherry","connectCode":{"code":"BOB#579"},"rankedNetplayProfile":{"id":"0xe0d573","ratingOrdinal":866.030815,"ratingUpdateCount":6,"wins":null,"losses":6,"dailyGlobalPlacement":null,"dailyRegionalPlacement":null,"continent":"NORTH_AMERICA","characters":[{"id":"0x1623d3f","character":"SHEIK","gameCount":11},{"id":"0x1623d40","character":"GAME_AND_WATCH","gameCount":2}]}}},"tag":"Cherry"},"BUU#888":{"getConnectCode":{"user":{"displayName":"Dost They Know?","connectCode":{"code":"BUU#888"},"rankedNetplayProfile":{"id":"0x2289c6","ratingOrdinal":1496.040078,"ratingUpdateCount":99,"wins":51,"losses":48,"dailyGlobalPlacement":null,"dailyRegionalPlacement":null,"continent":"NORTH_AMERICA","characters":[{"id":"0x159ec89","character":"MARTH","gameCount":160},{"id":"0x159ec8a","character":"FOX","gameCount":21},{"id":"0x159ec8b","character":"FALCO","gameCount":3}]}}},"tag":"CocaineMontana"},"CERT#605":{"getConnectCode":{"user":{"displayName":"Certy","connectCode":{"code":"CERT#605"},"rankedNetplayProfile":{"id":"0x11f7ae6","ratingOrdinal":1362.136641,"ratingUpdateCount":390,"wins":198,"losses":192,"dailyGlobalPlacement":null,"dailyRegionalPlacement":null,"continent":"NORTH_AMERICA","characters":[{"id":"0x187228b","character":"ZELDA","gameCount":1},{"id":"0x187228c","character":"PEACH","gameCount":1},{"id":"0x187228d","character":"FOX","gameCount":11},{"id":"0x187228e","character":"FALCO","gameCount":842},{"id":"0x187228f","character":"SHEIK","gameCount":13}]}}},"tag":"Certy"},"CHAI#763":{"getConnectCode":{"user":{"displayName":"chair","connectCode":{"code":"CHAI#763"},"rankedNetplayProfile":{"id":"0x2423fb","ratingOrdinal":1460.593433,"ratingUpdateCount":358,"wins":182,"losses":176,"dailyGlobalPlacement":null,"dailyRegionalPlacement":null,"continent":"NORTH_AMERICA","characters":[{"id":"0x18e78ae","character":"FALCO","gameCount":458},{"id":"0x18e78af","character":"PEACH","gameCount":17},{"id":"0x18e78b0","character":"SAMUS","gameCount":1},{"id":"0x18e78b1","character":"FOX","gameCount":4},{"id":"0x18e78b2","character":"ICE_CLIMBERS","gameCount":1},{"id":"0x18e78b3","character":"YOUNG_LINK","gameCount":15},{"id":"0x18e78b4","character":"JIGGLYPUFF","gameCount":3},{"id":"0x18e78b5","character":"SHEIK","gameCount":202},{"id":"0x18e78b6","character":"MARTH","gameCount":68},{"id":"0x18e78b7","character":"GANONDORF","gameCount":1}]}}},"tag":"Chair"},"CHEF#249":{"getConnectCode":{"user":{"displayName":"Video James","connectCode":{"code":"CHEF#249"},"rankedNetplayProfile":{"id":"0x2c6161","ratingOrdinal":1686.226736,"ratingUpdateCount":202,"wins":100,"losses":102,"dailyGlobalPlacement":null,"dailyRegionalPlacement":null,"continent":"NORTH_AMERICA","characters":[{"id":"0x1533bb6","character":"GAME_AND_WATCH","gameCount":443},{"id":"0x1533bb7","character":"FOX","gameCount":13},{"id":"0x1533bb8","character":"MARTH","gameCount":1}]}}},"tag":"Chef Royardee"},"CHEF#330":{"getConnectCode":{"user":{"displayName":"Lil Moser","connectCode":{"code":"CHEF#330"},"rankedNetplayProfile":{"id":"0x2f36d0","ratingOrdinal":2342.690458,"ratingUpdateCount":377,"wins":216,"losses":161,"dailyGlobalPlacement":null,"dailyRegionalPlacement":null,"continent":"NORTH_AMERICA","characters":[{"id":"0x18f1667","character":"FOX","gameCount":870},{"id":"0x18f1668","character":"FALCO","gameCount":3},{"id":"0x18f1669","character":"MARIO","gameCount":1},{"id":"0x18f166a","character":"CAPTAIN_FALCON","gameCount":2},{"id":"0x18f1cfd","character":"SHEIK","gameCount":1}]}}},"tag":""},"CLMG#449":{"getConnectCode":{"user":{"displayName":"ChicagOAT","connectCode":{"code":"CLMG#449"},"rankedNetplayProfile":{"id":"0x1bad9e6","ratingOrdinal":2119.268569,"ratingUpdateCount":86,"wins":50,"losses":36,"dailyGlobalPlacement":null,"dailyRegionalPlacement":null,"continent":"NORTH_AMERICA","characters":[{"id":"0x1baddeb","character":"MEWTWO","gameCount":206}]}}},"tag":""},"CLONE#2":{"getConnectCode":{"user":{"displayName":"BinaryClone","connectCode":{"code":"CLONE#2"},"rankedNetplayProfile":{"id":"0x229168","ratingOrdinal":1791.765951,"ratingUpdateCount":36,"wins":22,"losses":14,"dailyGlobalPlacement":null,"dailyRegionalPlacement":null,"continent":"NORTH_AMERICA","characters":[{"id":"0x229bb6","character":"FOX","gameCount":81}]}}},"tag":"Binary Clone"},"COR#489":{"getConnectCode":{"user":{"displayName":"learning to f1y","connectCode":{"code":"COR#489"},"rankedNetplayProfile":{"id":"0x25aaa4","ratingOrdinal":1940.850134,"ratingUpdateCount":214,"wins":116,"losses":98,"dailyGlobalPlacement":null,"dailyRegionalPlacement":null,"continent":"NORTH_AMERICA","characters":[{"id":"0x143cea3","character":"FOX","gameCount":4},{"id":"0x143cea4","character":"FALCO","gameCount":3},{"id":"0x143cea5","character":"SHEIK","gameCount":421},{"id":"0x143cea6","character":"ZELDA","gameCount":3},{"id":"0x143cea7","character":"MARTH","gameCount":38},{"id":"0x143cea8","character":"CAPTAIN_FALCON","gameCount":5},{"id":"0x15ac28b","character":"JIGGLYPUFF","gameCount":1},{"id":"0x1658ba2","character":"DONKEY_KONG","gameCount":3}]}}},"tag":"evil lesbian"},"CRJ#913":{"getConnectCode":{"user":{"displayName":"carlyraejepsen","connectCode":{"code":"CRJ#913"},"rankedNetplayProfile":{"id":"0x255816","ratingOrdinal":1498.572288,"ratingUpdateCount":144,"wins":73,"losses":71,"dailyGlobalPlacement":null,"dailyRegionalPlacement":null,"continent":"NORTH_AMERICA","characters":[{"id":"0x1288f69","character":"JIGGLYPUFF","gameCount":152},{"id":"0x1288f6a","character":"SHEIK","gameCount":34},{"id":"0x1288f6b","character":"GANONDORF","gameCount":57},{"id":"0x1288f6c","character":"FOX","gameCount":33},{"id":"0x1288f6d","character":"ZELDA","gameCount":1},{"id":"0x1288f6e","character":"BOWSER","gameCount":35},{"id":"0x1288f6f","character":"MARTH","gameCount":1}]}}},"tag":"kenny"},"CTYP#13":{"getConnectCode":{"user":{"displayName":"CTYP","connectCode":{"code":"CTYP#13"},"rankedNetplayProfile":{"id":"0x2326bb","ratingOrdinal":1243.416272,"ratingUpdateCount":26,"wins":12,"losses":14,"dailyGlobalPlacement":null,"dailyRegionalPlacement":null,"continent":"NORTH_AMERICA","characters":[{"id":"0x473b7d","character":"YOSHI","gameCount":50},{"id":"0x47509d","character":"FALCO","gameCount":3},{"id":"0x47e389","character":"FOX","gameCount":8}]}}},"tag":""},"DOCT#754":{"getConnectCode":{"user":{"displayName":"doctahdylan","connectCode":{"code":"DOCT#754"},"rankedNetplayProfile":{"id":"0x227fc7","ratingOrdinal":1831.839252,"ratingUpdateCount":719,"wins":357,"losses":362,"dailyGlobalPlacement":null,"dailyRegionalPlacement":null,"continent":"NORTH_AMERICA","characters":[{"id":"0x1883597","character":"MARTH","gameCount":3},{"id":"0x1883598","character":"CAPTAIN_FALCON","gameCount":1412},{"id":"0x1883599","character":"FALCO","gameCount":6},{"id":"0x188359a","character":"GANONDORF","gameCount":37},{"id":"0x188359b","character":"FOX","gameCount":1},{"id":"0x188359c","character":"DONKEY_KONG","gameCount":60}]}}},"tag":"doctahdylan"},"DOG#0":{"getConnectCode":{"user":{"displayName":"the wise miser","connectCode":{"code":"DOG#0"},"rankedNetplayProfile":{"id":"0x24bb0a","ratingOrdinal":1571.540566,"ratingUpdateCount":50,"wins":28,"losses":22,"dailyGlobalPlacement":null,"dailyRegionalPlacement":null,"continent":"NORTH_AMERICA","characters":[{"id":"0x18e64af","character":"FOX","gameCount":37},{"id":"0x18e64b0","character":"MARTH","gameCount":58},{"id":"0x18e64b1","character":"FALCO","gameCount":8},{"id":"0x18e64b2","character":"CAPTAIN_FALCON","gameCount":1}]}}},"tag":"inu"},"DRAG#104":{"getConnectCode":{"user":{"displayName":"Dragoid","connectCode":{"code":"DRAG#104"},"rankedNetplayProfile":{"id":"0x224829","ratingOrdinal":2211.675595,"ratingUpdateCount":405,"wins":224,"losses":181,"dailyGlobalPlacement":null,"dailyRegionalPlacement":null,"continent":"NORTH_AMERICA","characters":[{"id":"0x1aefc7c","character":"FALCO","gameCount":858},{"id":"0x1aefc7d","character":"FOX","gameCount":4}]}}},"tag":"Dragoid"},"DRJR#111":{"getConnectCode":{"user":{"displayName":"TheDoctorJR","connectCode":{"code":"DRJR#111"},"rankedNetplayProfile":{"id":"0x229dc3","ratingOrdinal":1493.257719,"ratingUpdateCount":2669,"wins":1339,"losses":1330,"dailyGlobalPlacement":null,"dailyRegionalPlacement":null,"continent":"NORTH_AMERICA","characters":[{"id":"0x1866092","character":"LUIGI","gameCount":10},{"id":"0x1866093","character":"FALCO","gameCount":5573},{"id":"0x1866094","character":"JIGGLYPUFF","gameCount":7},{"id":"0x1866095","character":"PEACH","gameCount":6}]}}},"tag":""},"EDOC#161":{"getConnectCode":{"user":{"displayName":"Edoc","connectCode":{"code":"EDOC#161"},"rankedNetplayProfile":{"id":"0xfaad7b","ratingOrdinal":1100,"ratingUpdateCount":0,"wins":null,"losses":null,"dailyGlobalPlacement":null,"dailyRegionalPlacement":null,"continent":null,"characters":[]}}},"tag":"EDOC"},"EVA#01":{"getConnectCode":{"user":{"displayName":"George Costanza","connectCode":{"code":"EVA#01"},"rankedNetplayProfile":{"id":"0x222977","ratingOrdinal":1767.975826,"ratingUpdateCount":168,"wins":89,"losses":79,"dailyGlobalPlacement":null,"dailyRegionalPlacement":null,"continent":"NORTH_AMERICA","characters":[{"id":"0x256d01","character":"PEACH","gameCount":212},{"id":"0x25bf89","character":"FOX","gameCount":186}]}}},"tag":"Phalanx"},"FAST#878":{"getConnectCode":{"user":{"displayName":"Fasthands","connectCode":{"code":"FAST#878"},"rankedNetplayProfile":{"id":"0x29a379","ratingOrdinal":2004.352375,"ratingUpdateCount":1576,"wins":782,"losses":794,"dailyGlobalPlacement":null,"dailyRegionalPlacement":null,"continent":"NORTH_AMERICA","characters":[{"id":"0x188783e","character":"MEWTWO","gameCount":3257},{"id":"0x188783f","character":"FALCO","gameCount":9}]}}},"tag":"Fasthands"},"FERO#866":{"getConnectCode":{"user":{"displayName":"ferocitii","connectCode":{"code":"FERO#866"},"rankedNetplayProfile":{"id":"0x36449d","ratingOrdinal":2345.293676,"ratingUpdateCount":317,"wins":223,"losses":94,"dailyGlobalPlacement":null,"dailyRegionalPlacement":null,"continent":"NORTH_AMERICA","characters":[{"id":"0x196ad03","character":"DONKEY_KONG","gameCount":4},{"id":"0x196ad04","character":"PEACH","gameCount":599},{"id":"0x196ad05","character":"FALCO","gameCount":3},{"id":"0x196ad06","character":"FOX","gameCount":24},{"id":"0x196ad07","character":"MARTH","gameCount":4}]}}},"tag":"Ferocitii"},"FISH#157":{"getConnectCode":{"user":{"displayName":"Blowfishh","connectCode":{"code":"FISH#157"},"rankedNetplayProfile":{"id":"0x255b55","ratingOrdinal":1393.516461,"ratingUpdateCount":148,"wins":79,"losses":69,"dailyGlobalPlacement":null,"dailyRegionalPlacement":null,"continent":"NORTH_AMERICA","characters":[{"id":"0x198e83a","character":"JIGGLYPUFF","gameCount":10},{"id":"0x198e83b","character":"FALCO","gameCount":33},{"id":"0x198e83c","character":"DR_MARIO","gameCount":6},{"id":"0x198e83d","character":"MARTH","gameCount":10},{"id":"0x198e83e","character":"LUIGI","gameCount":5},{"id":"0x198e83f","character":"FOX","gameCount":11},{"id":"0x198e840","character":"ROY","gameCount":11},{"id":"0x198e841","character":"YOSHI","gameCount":9},{"id":"0x198e842","character":"GAME_AND_WATCH","gameCount":10},{"id":"0x198e843","character":"YOUNG_LINK","gameCount":9},{"id":"0x198e844","character":"DONKEY_KONG","gameCount":11},{"id":"0x198e845","character":"NESS","gameCount":9},{"id":"0x198e846","character":"SHEIK","gameCount":11},{"id":"0x198e847","character":"LINK","gameCount":16},{"id":"0x198e848","character":"GANONDORF","gameCount":19},{"id":"0x198e849","character":"ZELDA","gameCount":4},{"id":"0x198e84a","character":"SAMUS","gameCount":11},{"id":"0x198e84b","character":"CAPTAIN_FALCON","gameCount":13},{"id":"0x198e84c","character":"PICHU","gameCount":10},{"id":"0x198e84d","character":"PEACH","gameCount":9},{"id":"0x198e84e","character":"KIRBY","gameCount":13},{"id":"0x198e84f","character":"MARIO","gameCount":11},{"id":"0x198e850","character":"BOWSER","gameCount":6},{"id":"0x198e851","character":"PIKACHU","gameCount":8},{"id":"0x198e852","character":"MEWTWO","gameCount":4},{"id":"0x198e853","character":"ICE_CLIMBERS","gameCount":7}]}}},"tag":""},"FOXC#928":{"getConnectCode":{"user":{"displayName":"FoxCap","connectCode":{"code":"FOXC#928"},"rankedNetplayProfile":{"id":"0x2544ba","ratingOrdinal":2157.837444,"ratingUpdateCount":798,"wins":458,"losses":340,"dailyGlobalPlacement":null,"dailyRegionalPlacement":null,"continent":"NORTH_AMERICA","characters":[{"id":"0x18a6422","character":"FOX","gameCount":1753},{"id":"0x18a6423","character":"FALCO","gameCount":4},{"id":"0x1c14cf6","character":"SHEIK","gameCount":1}]}}},"tag":"FoxCap"},"FRST#600":{"getConnectCode":{"user":{"displayName":"TTV/Frost_117","connectCode":{"code":"FRST#600"},"rankedNetplayProfile":{"id":"0x231833","ratingOrdinal":2178.477487,"ratingUpdateCount":589,"wins":328,"losses":261,"dailyGlobalPlacement":null,"dailyRegionalPlacement":null,"continent":"NORTH_AMERICA","characters":[{"id":"0x18aaabe","character":"SAMUS","gameCount":1337}]}}},"tag":"Frost"},"GEC#796":{"getConnectCode":{"user":{"displayName":"rowan!","connectCode":{"code":"GEC#796"},"rankedNetplayProfile":{"id":"0x22fb39","ratingOrdinal":1596.295872,"ratingUpdateCount":141,"wins":74,"losses":67,"dailyGlobalPlacement":null,"dailyRegionalPlacement":null,"continent":"NORTH_AMERICA","characters":[{"id":"0x147217e","character":"FALCO","gameCount":1},{"id":"0x147217f","character":"FOX","gameCount":5},{"id":"0x1472180","character":"SHEIK","gameCount":2},{"id":"0x1472181","character":"PIKACHU","gameCount":14},{"id":"0x1472182","character":"MARTH","gameCount":256}]}}},"tag":"saffron"},"GIOG#435":{"getConnectCode":{"user":{"displayName":"GI0GOAT","connectCode":{"code":"GIOG#435"},"rankedNetplayProfile":{"id":"0x28aa42","ratingOrdinal":2042.977854,"ratingUpdateCount":120,"wins":68,"losses":52,"dailyGlobalPlacement":null,"dailyRegionalPlacement":null,"continent":"NORTH_AMERICA","characters":[{"id":"0x1a42587","character":"FOX","gameCount":277},{"id":"0x1a42588","character":"KIRBY","gameCount":1}]}}},"tag":"GI0GOAT"},"GLOS#194":{"getConnectCode":{"user":{"displayName":"g'Loss","connectCode":{"code":"GLOS#194"},"rankedNetplayProfile":{"id":"0x1768664","ratingOrdinal":2215.542784,"ratingUpdateCount":187,"wins":97,"losses":90,"dailyGlobalPlacement":null,"dailyRegionalPlacement":null,"continent":"NORTH_AMERICA","characters":[{"id":"0x189344f","character":"FOX","gameCount":3},{"id":"0x1893450","character":"SHEIK","gameCount":431},{"id":"0x18bd591","character":"PEACH","gameCount":6},{"id":"0x18e791b","character":"MARTH","gameCount":2}]}}},"tag":"lovestory4a"},"HAZE#446":{"getConnectCode":{"user":{"displayName":"DumbestGrlAlive","connectCode":{"code":"HAZE#446"},"rankedNetplayProfile":{"id":"0x237c11","ratingOrdinal":1490.455282,"ratingUpdateCount":78,"wins":38,"losses":40,"dailyGlobalPlacement":null,"dailyRegionalPlacement":null,"continent":"NORTH_AMERICA","characters":[{"id":"0x1a0d9a8","character":"MARTH","gameCount":1},{"id":"0x1a0d9a9","character":"ZELDA","gameCount":1},{"id":"0x1a0d9aa","character":"FOX","gameCount":137},{"id":"0x1a0d9ab","character":"SHEIK","gameCount":13}]}}},"tag":"TS Popstar"},"HDUB#254":{"getConnectCode":{"user":{"displayName":"hdubbz","connectCode":{"code":"HDUB#254"},"rankedNetplayProfile":{"id":"0x35c95e","ratingOrdinal":1289.120467,"ratingUpdateCount":242,"wins":116,"losses":126,"dailyGlobalPlacement":null,"dailyRegionalPlacement":null,"continent":"NORTH_AMERICA","characters":[{"id":"0x143b583","character":"MARTH","gameCount":8},{"id":"0x143b584","character":"SHEIK","gameCount":484},{"id":"0x143b585","character":"FOX","gameCount":25}]}}},"tag":"Welsh Rabbit"},"HONK#595":{"getConnectCode":{"user":{"displayName":"goosyyyy :3","connectCode":{"code":"HONK#595"},"rankedNetplayProfile":{"id":"0x249a5c","ratingOrdinal":1042.677636,"ratingUpdateCount":748,"wins":343,"losses":405,"dailyGlobalPlacement":null,"dailyRegionalPlacement":null,"continent":"NORTH_AMERICA","characters":[{"id":"0x18a8dd9","character":"FOX","gameCount":459},{"id":"0x18a8dda","character":"DONKEY_KONG","gameCount":29},{"id":"0x18a8ddb","character":"YOSHI","gameCount":4},{"id":"0x18a8ddc","character":"MARTH","gameCount":11},{"id":"0x18a8ddd","character":"ICE_CLIMBERS","gameCount":3},{"id":"0x18a8dde","character":"YOUNG_LINK","gameCount":11},{"id":"0x18a8ddf","character":"DR_MARIO","gameCount":3},{"id":"0x18a8de0","character":"PIKACHU","gameCount":1},{"id":"0x18a8de1","character":"PEACH","gameCount":12},{"id":"0x18a8de2","character":"NESS","gameCount":2},{"id":"0x18a8de3","character":"SAMUS","gameCount":2},{"id":"0x18a8de4","character":"SHEIK","gameCount":661},{"id":"0x18a8de5","character":"MEWTWO","gameCount":2},{"id":"0x18a8de6","character":"FALCO","gameCount":318},{"id":"0x18a8de7","character":"MARIO","gameCount":11}]}}},"tag":"Goose447"},"HYUN#518":{"getConnectCode":{"user":{"displayName":"hyunnies","connectCode":{"code":"HYUN#518"},"rankedNetplayProfile":{"id":"0x35faf7","ratingOrdinal":2209.825937,"ratingUpdateCount":663,"wins":356,"losses":307,"dailyGlobalPlacement":null,"dailyRegionalPlacement":null,"continent":"NORTH_AMERICA","characters":[{"id":"0x188ab68","character":"MARTH","gameCount":1231}]}}},"tag":"Hyunnies"},"IPPO#355":{"getConnectCode":{"user":{"displayName":"lokochon","connectCode":{"code":"IPPO#355"},"rankedNetplayProfile":{"id":"0x269d08","ratingOrdinal":1634.19912,"ratingUpdateCount":58,"wins":29,"losses":29,"dailyGlobalPlacement":null,"dailyRegionalPlacement":null,"continent":"NORTH_AMERICA","characters":[{"id":"0x14ff07a","character":"PEACH","gameCount":83},{"id":"0x14ff07b","character":"FALCO","gameCount":7},{"id":"0x14ff07c","character":"CAPTAIN_FALCON","gameCount":1},{"id":"0x14ff07d","character":"FOX","gameCount":26}]}}},"tag":"Dempsey Roll"},"IWTR#106":{"getConnectCode":{"user":{"displayName":"iBeDrinkinWater","connectCode":{"code":"IWTR#106"},"rankedNetplayProfile":{"id":"0x54e553","ratingOrdinal":1438.752114,"ratingUpdateCount":10,"wins":6,"losses":4,"dailyGlobalPlacement":null,"dailyRegionalPlacement":null,"continent":"NORTH_AMERICA","characters":[{"id":"0x15720cb","character":"FOX","gameCount":23}]}}},"tag":"VibeWater"},"JAIRTHECREATOR#711":{"getConnectCode":null,"tag":"Jair"},"JNDY#113":{"getConnectCode":{"user":{"displayName":"Johnny Tsunami","connectCode":{"code":"JNDY#113"},"rankedNetplayProfile":{"id":"0x27ef29","ratingOrdinal":1522.569405,"ratingUpdateCount":282,"wins":149,"losses":133,"dailyGlobalPlacement":null,"dailyRegionalPlacement":null,"continent":"NORTH_AMERICA","characters":[{"id":"0x11438f8","character":"PEACH","gameCount":7},{"id":"0x11438f9","character":"MEWTWO","gameCount":1},{"id":"0x11438fa","character":"MARTH","gameCount":7},{"id":"0x11438fb","character":"FALCO","gameCount":7},{"id":"0x11438fc","character":"KIRBY","gameCount":1},{"id":"0x11438fd","character":"GANONDORF","gameCount":1},{"id":"0x11438fe","character":"DONKEY_KONG","gameCount":1},{"id":"0x11438ff","character":"JIGGLYPUFF","gameCount":11},{"id":"0x1143900","character":"LUIGI","gameCount":1},{"id":"0x1143901","character":"FOX","gameCount":411},{"id":"0x1143902","character":"PIKACHU","gameCount":2},{"id":"0x1143903","character":"YOSHI","gameCount":1},{"id":"0x1143904","character":"CAPTAIN_FALCON","gameCount":16},{"id":"0x1143905","character":"SHEIK","gameCount":3}]}}},"tag":"Jandy"},"JTC#711":{"getConnectCode":{"user":{"displayName":"JairtheCreator","connectCode":{"code":"JTC#711"},"rankedNetplayProfile":{"id":"0x2b6a1c","ratingOrdinal":2014.282769,"ratingUpdateCount":420,"wins":211,"losses":209,"dailyGlobalPlacement":null,"dailyRegionalPlacement":null,"continent":"NORTH_AMERICA","characters":[{"id":"0x2f112a","character":"ICE_CLIMBERS","gameCount":799},{"id":"0x562c94","character":"ZELDA","gameCount":1},{"id":"0x5a0cca","character":"DR_MARIO","gameCount":1},{"id":"0x6e56af","character":"SHEIK","gameCount":11}]}}},"tag":"JairtheCreator"},"KAIS#283":{"getConnectCode":{"user":{"displayName":"Kaiser","connectCode":{"code":"KAIS#283"},"rankedNetplayProfile":{"id":"0x22f68b","ratingOrdinal":1826.270852,"ratingUpdateCount":184,"wins":94,"losses":90,"dailyGlobalPlacement":null,"dailyRegionalPlacement":null,"continent":"NORTH_AMERICA","characters":[{"id":"0x1b85842","character":"FOX","gameCount":3},{"id":"0x1b85843","character":"FALCO","gameCount":261},{"id":"0x1b85844","character":"SHEIK","gameCount":4}]}}},"tag":"Kaiser"},"KBLU#157":{"getConnectCode":{"user":{"displayName":"Dynokid04","connectCode":{"code":"KBLU#157"},"rankedNetplayProfile":{"id":"0x27a605","ratingOrdinal":2220.298285,"ratingUpdateCount":595,"wins":359,"losses":236,"dailyGlobalPlacement":null,"dailyRegionalPlacement":null,"continent":"NORTH_AMERICA","characters":[{"id":"0x190573b","character":"FALCO","gameCount":1223}]}}},"tag":""},"KIBS#345":{"getConnectCode":{"user":{"displayName":"Forestz","connectCode":{"code":"KIBS#345"},"rankedNetplayProfile":{"id":"0x27333a","ratingOrdinal":1757.367345,"ratingUpdateCount":71,"wins":38,"losses":33,"dailyGlobalPlacement":null,"dailyRegionalPlacement":null,"continent":"NORTH_AMERICA","characters":[{"id":"0x144653e","character":"MARTH","gameCount":1},{"id":"0x144653f","character":"YOSHI","gameCount":152}]}}},"tag":"Kibby"},"KIWI#0":{"getConnectCode":{"user":{"displayName":"Malaise","connectCode":{"code":"KIWI#0"},"rankedNetplayProfile":{"id":"0x226d78","ratingOrdinal":1637.226698,"ratingUpdateCount":235,"wins":126,"losses":109,"dailyGlobalPlacement":null,"dailyRegionalPlacement":null,"continent":"NORTH_AMERICA","characters":[{"id":"0x18b86f4","character":"SHEIK","gameCount":294},{"id":"0x18b86f5","character":"ZELDA","gameCount":2},{"id":"0x18b86f6","character":"JIGGLYPUFF","gameCount":10},{"id":"0x18b86f7","character":"FALCO","gameCount":4},{"id":"0x18b86f8","character":"FOX","gameCount":166}]}}},"tag":"Malaise"},"KNEE#860":{"getConnectCode":{"user":{"displayName":"HeartKnee","connectCode":{"code":"KNEE#860"},"rankedNetplayProfile":{"id":"0x223a55","ratingOrdinal":1327.516268,"ratingUpdateCount":21,"wins":10,"losses":11,"dailyGlobalPlacement":null,"dailyRegionalPlacement":null,"continent":"NORTH_AMERICA","characters":[{"id":"0x2c2491","character":"MARTH","gameCount":52}]}}},"tag":"HeartKnee"},"KOKO#520":{"getConnectCode":{"user":{"displayName":"ls4ashley","connectCode":{"code":"KOKO#520"},"rankedNetplayProfile":{"id":"0x24b998","ratingOrdinal":2280.423119,"ratingUpdateCount":1753,"wins":885,"losses":868,"dailyGlobalPlacement":null,"dailyRegionalPlacement":null,"continent":"NORTH_AMERICA","characters":[{"id":"0x19a4b7b","character":"JIGGLYPUFF","gameCount":13},{"id":"0x19a4b7c","character":"PEACH","gameCount":82},{"id":"0x19a4b7d","character":"FOX","gameCount":220},{"id":"0x19a4b7e","character":"MEWTWO","gameCount":1},{"id":"0x19a4b7f","character":"SHEIK","gameCount":3014},{"id":"0x19a4b80","character":"PIKACHU","gameCount":1},{"id":"0x19a4b81","character":"MARTH","gameCount":402},{"id":"0x19a4b82","character":"CAPTAIN_FALCON","gameCount":9},{"id":"0x19a4b83","character":"DR_MARIO","gameCount":3},{"id":"0x19a4b84","character":"FALCO","gameCount":26},{"id":"0x19a4b85","character":"ZELDA","gameCount":2},{"id":"0x1a2f73d","character":"ICE_CLIMBERS","gameCount":9}]}}},"tag":"lovestory4a"},"KUMS#104":{"getConnectCode":{"user":{"displayName":"kuMSa","connectCode":{"code":"KUMS#104"},"rankedNetplayProfile":{"id":"0x229508","ratingOrdinal":2202.083606,"ratingUpdateCount":438,"wins":224,"losses":214,"dailyGlobalPlacement":null,"dailyRegionalPlacement":null,"continent":"NORTH_AMERICA","characters":[{"id":"0x1ae5742","character":"YOSHI","gameCount":946},{"id":"0x1ae5743","character":"FALCO","gameCount":12},{"id":"0x1ae5744","character":"FOX","gameCount":2},{"id":"0x1ae5745","character":"JIGGLYPUFF","gameCount":3}]}}},"tag":"Kumi"},"KWAK#421":{"getConnectCode":{"user":{"displayName":"too chilly","connectCode":{"code":"KWAK#421"},"rankedNetplayProfile":{"id":"0x223756","ratingOrdinal":1587.863288,"ratingUpdateCount":162,"wins":82,"losses":80,"dailyGlobalPlacement":null,"dailyRegionalPlacement":null,"continent":"NORTH_AMERICA","characters":[{"id":"0x1a54af3","character":"FALCO","gameCount":300},{"id":"0x1a54af4","character":"CAPTAIN_FALCON","gameCount":7},{"id":"0x1a54af5","character":"FOX","gameCount":2},{"id":"0x1a54af6","character":"MARTH","gameCount":2}]}}},"tag":"kwak"},"LARF#476":{"getConnectCode":{"user":{"displayName":"Larfen","connectCode":{"code":"LARF#476"},"rankedNetplayProfile":{"id":"0x223319","ratingOrdinal":1910.66988,"ratingUpdateCount":381,"wins":195,"losses":186,"dailyGlobalPlacement":null,"dailyRegionalPlacement":null,"continent":"NORTH_AMERICA","characters":[{"id":"0x18c4228","character":"SHEIK","gameCount":807},{"id":"0x18c4229","character":"FOX","gameCount":38},{"id":"0x18c422a","character":"KIRBY","gameCount":14},{"id":"0x18c422b","character":"MARTH","gameCount":2}]}}},"tag":"Larfen"},"LE#0":{"getConnectCode":{"user":{"displayName":"Cousin Emilio","connectCode":{"code":"LE#0"},"rankedNetplayProfile":{"id":"0x22589a","ratingOrdinal":1881.532105,"ratingUpdateCount":291,"wins":150,"losses":141,"dailyGlobalPlacement":null,"dailyRegionalPlacement":null,"continent":"NORTH_AMERICA","characters":[{"id":"0x190f2b4","character":"JIGGLYPUFF","gameCount":1},{"id":"0x190f2b5","character":"MARTH","gameCount":647},{"id":"0x190f2b6","character":"DONKEY_KONG","gameCount":3},{"id":"0x190f2b7","character":"FOX","gameCount":7}]}}},"tag":"Leo"},"LEO#748":{"getConnectCode":{"user":{"displayName":"Landlord","connectCode":{"code":"LEO#748"},"rankedNetplayProfile":{"id":"0x5da786","ratingOrdinal":1349.671324,"ratingUpdateCount":109,"wins":53,"losses":56,"dailyGlobalPlacement":null,"dailyRegionalPlacement":null,"continent":"NORTH_AMERICA","characters":[{"id":"0x14e416a","character":"CAPTAIN_FALCON","gameCount":198},{"id":"0x14e416b","character":"YOUNG_LINK","gameCount":9},{"id":"0x14e416c","character":"MARTH","gameCount":1}]}}},"tag":"Landlord"},"LEXI#750":{"getConnectCode":{"user":{"displayName":"gridlockEnjoyer","connectCode":{"code":"LEXI#750"},"rankedNetplayProfile":{"id":"0x2bc4d1","ratingOrdinal":1709.390114,"ratingUpdateCount":33,"wins":21,"losses":12,"dailyGlobalPlacement":null,"dailyRegionalPlacement":null,"continent":"NORTH_AMERICA","characters":[{"id":"0x15884db","character":"SHEIK","gameCount":55}]}}},"tag":"lexi!"},"LUPPI#91":{"getConnectCode":{"user":{"displayName":"Luppi","connectCode":{"code":"LUPPI#91"},"rankedNetplayProfile":{"id":"0x8474fd","ratingOrdinal":1532.085697,"ratingUpdateCount":40,"wins":19,"losses":22,"dailyGlobalPlacement":null,"dailyRegionalPlacement":null,"continent":"NORTH_AMERICA","characters":[{"id":"0x18de3e3","character":"FALCO","gameCount":97}]}}},"tag":"Luppi"},"M#2":{"getConnectCode":{"user":{"displayName":"mattpopa","connectCode":{"code":"M#2"},"rankedNetplayProfile":{"id":"0x80a937","ratingOrdinal":1758.870453,"ratingUpdateCount":75,"wins":41,"losses":34,"dailyGlobalPlacement":null,"dailyRegionalPlacement":null,"continent":"NORTH_AMERICA","characters":[{"id":"0x127421e","character":"FOX","gameCount":168}]}}},"tag":""},"MACK#463":{"getConnectCode":{"user":{"displayName":"swt gimrs fault","connectCode":{"code":"MACK#463"},"rankedNetplayProfile":{"id":"0x33a407","ratingOrdinal":1456.331759,"ratingUpdateCount":107,"wins":54,"losses":53,"dailyGlobalPlacement":null,"dailyRegionalPlacement":null,"continent":"NORTH_AMERICA","characters":[{"id":"0x33a98d","character":"FOX","gameCount":257}]}}},"tag":"Mackcub"},"MEKK#251":{"getConnectCode":{"user":{"displayName":"Mekk","connectCode":{"code":"MEKK#251"},"rankedNetplayProfile":{"id":"0x2cd899","ratingOrdinal":2776.47644,"ratingUpdateCount":1652,"wins":1284,"losses":368,"dailyGlobalPlacement":13,"dailyRegionalPlacement":11,"continent":"NORTH_AMERICA","characters":[{"id":"0x18656da","character":"GANONDORF","gameCount":2922}]}}},"tag":"Mekk"},"MELA#877":{"getConnectCode":{"user":{"displayName":"ibdwfan2009","connectCode":{"code":"MELA#877"},"rankedNetplayProfile":{"id":"0x291c19","ratingOrdinal":1625.950859,"ratingUpdateCount":182,"wins":96,"losses":86,"dailyGlobalPlacement":null,"dailyRegionalPlacement":null,"continent":"NORTH_AMERICA","characters":[{"id":"0x14cf269","character":"FALCO","gameCount":327},{"id":"0x14cf26a","character":"MARTH","gameCount":11},{"id":"0x14cf26b","character":"ZELDA","gameCount":2},{"id":"0x14cf26c","character":"FOX","gameCount":6},{"id":"0x14cf26d","character":"GAME_AND_WATCH","gameCount":1},{"id":"0x14cf26e","character":"PICHU","gameCount":1},{"id":"0x14cf26f","character":"SHEIK","gameCount":3},{"id":"0x1608aaa","character":"MARIO","gameCount":2}]}}},"tag":"melatonin"},"MICH#623":{"getConnectCode":{"user":{"displayName":"Michael","connectCode":{"code":"MICH#623"},"rankedNetplayProfile":{"id":"0x458af5","ratingOrdinal":2534.27986,"ratingUpdateCount":459,"wins":350,"losses":109,"dailyGlobalPlacement":108,"dailyRegionalPlacement":95,"continent":"NORTH_AMERICA","characters":[{"id":"0x1a6e346","character":"JIGGLYPUFF","gameCount":898}]}}},"tag":"Michael"},"MILE#159":{"getConnectCode":{"user":{"displayName":"Miles","connectCode":{"code":"MILE#159"},"rankedNetplayProfile":{"id":"0x22c9f3","ratingOrdinal":1503.530036,"ratingUpdateCount":132,"wins":64,"losses":68,"dailyGlobalPlacement":null,"dailyRegionalPlacement":null,"continent":"NORTH_AMERICA","characters":[{"id":"0x10174eb","character":"SHEIK","gameCount":1},{"id":"0x111c567","character":"FOX","gameCount":1},{"id":"0x111c568","character":"FALCO","gameCount":193},{"id":"0x111c569","character":"MARTH","gameCount":2},{"id":"0x111c56a","character":"ZELDA","gameCount":8}]}}},"tag":"JeffS"},"MOY#56":{"getConnectCode":{"user":{"displayName":"moy, slimey","connectCode":{"code":"MOY#56"},"rankedNetplayProfile":{"id":"0x256028","ratingOrdinal":1725.243872,"ratingUpdateCount":16,"wins":11,"losses":5,"dailyGlobalPlacement":null,"dailyRegionalPlacement":null,"continent":"NORTH_AMERICA","characters":[{"id":"0x30c8f2","character":"CAPTAIN_FALCON","gameCount":37}]}}},"tag":""},"MRTH#856":{"getConnectCode":{"user":{"displayName":"mwat","connectCode":{"code":"MRTH#856"},"rankedNetplayProfile":{"id":"0x224faf","ratingOrdinal":1575.26,"ratingUpdateCount":451,"wins":226,"losses":225,"dailyGlobalPlacement":null,"dailyRegionalPlacement":null,"continent":"NORTH_AMERICA","characters":[{"id":"0x18849e4","character":"CAPTAIN_FALCON","gameCount":54},{"id":"0x18849e5","character":"JIGGLYPUFF","gameCount":1},{"id":"0x18849e6","character":"ROY","gameCount":2},{"id":"0x18849e7","character":"FALCO","gameCount":458},{"id":"0x18849e8","character":"FOX","gameCount":456}]}}},"tag":"Tawm"},"NACE#720":{"getConnectCode":{"user":{"displayName":"@exechks","connectCode":{"code":"NACE#720"},"rankedNetplayProfile":{"id":"0x22b179","ratingOrdinal":1551.176845,"ratingUpdateCount":59,"wins":32,"losses":27,"dailyGlobalPlacement":null,"dailyRegionalPlacement":null,"continent":"NORTH_AMERICA","characters":[{"id":"0x15d900a","character":"FOX","gameCount":141}]}}},"tag":"ex"},"NARA#320":{"getConnectCode":{"user":{"displayName":"Nara","connectCode":{"code":"NARA#320"},"rankedNetplayProfile":{"id":"0x23b17e","ratingOrdinal":1615.931117,"ratingUpdateCount":487,"wins":246,"losses":241,"dailyGlobalPlacement":null,"dailyRegionalPlacement":null,"continent":"NORTH_AMERICA","characters":[{"id":"0xf5b62e","character":"DR_MARIO","gameCount":1},{"id":"0x10eb4f0","character":"SAMUS","gameCount":16},{"id":"0x10eb4f1","character":"JIGGLYPUFF","gameCount":1},{"id":"0x10eb4f2","character":"SHEIK","gameCount":2},{"id":"0x10eb4f3","character":"MARTH","gameCount":3},{"id":"0x10eb4f4","character":"PEACH","gameCount":2},{"id":"0x10eb4f5","character":"FALCO","gameCount":941},{"id":"0x10eb4f6","character":"ROY","gameCount":1},{"id":"0x10eb4f7","character":"FOX","gameCount":3},{"id":"0x10eb4f8","character":"LUIGI","gameCount":1}]}}},"tag":""},"NATO#281":{"getConnectCode":{"user":{"displayName":"Nato","connectCode":{"code":"NATO#281"},"rankedNetplayProfile":{"id":"0xa05987","ratingOrdinal":902.734487,"ratingUpdateCount":263,"wins":111,"losses":152,"dailyGlobalPlacement":null,"dailyRegionalPlacement":null,"continent":"NORTH_AMERICA","characters":[{"id":"0x18e9386","character":"MARTH","gameCount":422}]}}},"tag":"Nato"},"NOFL#113":{"getConnectCode":{"user":{"displayName":"Anti-Hero","connectCode":{"code":"NOFL#113"},"rankedNetplayProfile":{"id":"0x43cdb3","ratingOrdinal":2392.151661,"ratingUpdateCount":488,"wins":364,"losses":124,"dailyGlobalPlacement":244,"dailyRegionalPlacement":null,"continent":"NORTH_AMERICA","characters":[{"id":"0x1b2522c","character":"GANONDORF","gameCount":949}]}}},"tag":"Anti-Hero"},"NOTC#746":{"getConnectCode":{"user":{"displayName":"SprintAtWomen","connectCode":{"code":"NOTC#746"},"rankedNetplayProfile":{"id":"0x2bbfe2","ratingOrdinal":1881.303513,"ratingUpdateCount":18,"wins":15,"losses":3,"dailyGlobalPlacement":null,"dailyRegionalPlacement":null,"continent":"NORTH_AMERICA","characters":[{"id":"0x15d29f8","character":"FALCO","gameCount":39},{"id":"0x15d29f9","character":"FOX","gameCount":2}]}}},"tag":"N0tch"},"NOX #359":{"getConnectCode":null,"tag":"Nox"},"NOX#359":{"getConnectCode":{"user":{"displayName":"Nox","connectCode":{"code":"NOX#359"},"rankedNetplayProfile":{"id":"0x306a62","ratingOrdinal":2026.667682,"ratingUpdateCount":253,"wins":126,"losses":127,"dailyGlobalPlacement":null,"dailyRegionalPlacement":null,"continent":"NORTH_AMERICA","characters":[{"id":"0x1a157a5","character":"FALCO","gameCount":66},{"id":"0x1a157a6","character":"FOX","gameCount":187},{"id":"0x1a157a7","character":"CAPTAIN_FALCON","gameCount":137},{"id":"0x1a157a8","character":"SHEIK","gameCount":110},{"id":"0x1a157a9","character":"MARIO","gameCount":5},{"id":"0x1a157aa","character":"MARTH","gameCount":3}]}}},"tag":"nox"},"NYCK#483":{"getConnectCode":{"user":{"displayName":"nyck","connectCode":{"code":"NYCK#483"},"rankedNetplayProfile":{"id":"0x23f1be","ratingOrdinal":1406.555496,"ratingUpdateCount":21,"wins":11,"losses":10,"dailyGlobalPlacement":null,"dailyRegionalPlacement":null,"continent":"NORTH_AMERICA","characters":[{"id":"0x411466","character":"LUIGI","gameCount":48}]}}},"tag":"nyck"},"OATH#805":{"getConnectCode":{"user":{"displayName":"Oathlivion","connectCode":{"code":"OATH#805"},"rankedNetplayProfile":{"id":"0x23714c","ratingOrdinal":1604.531444,"ratingUpdateCount":35,"wins":20,"losses":15,"dailyGlobalPlacement":null,"dailyRegionalPlacement":null,"continent":"NORTH_AMERICA","characters":[{"id":"0x238103","character":"FALCO","gameCount":81}]}}},"tag":"Oathlivion"},"OBER#178":{"getConnectCode":{"user":{"displayName":"GPBR","connectCode":{"code":"OBER#178"},"rankedNetplayProfile":{"id":"0x223995","ratingOrdinal":2435.273212,"ratingUpdateCount":188,"wins":131,"losses":57,"dailyGlobalPlacement":187,"dailyRegionalPlacement":null,"continent":"NORTH_AMERICA","characters":[{"id":"0x18b93d7","character":"SHEIK","gameCount":3},{"id":"0x18b93d8","character":"FALCO","gameCount":436}]}}},"tag":"Ober"},"OMEN#438":{"getConnectCode":{"user":{"displayName":"Omenga","connectCode":{"code":"OMEN#438"},"rankedNetplayProfile":{"id":"0x2a45fc","ratingOrdinal":1141.863659,"ratingUpdateCount":67,"wins":28,"losses":39,"dailyGlobalPlacement":null,"dailyRegionalPlacement":null,"continent":"NORTH_AMERICA","characters":[{"id":"0x2a52a9","character":"MARTH","gameCount":83},{"id":"0x2a52aa","character":"DR_MARIO","gameCount":3},{"id":"0x2abea4","character":"FALCO","gameCount":14},{"id":"0x4c04eb","character":"FOX","gameCount":14},{"id":"0x5af2c4","character":"BOWSER","gameCount":1},{"id":"0x5aff91","character":"JIGGLYPUFF","gameCount":6},{"id":"0x5b1bbc","character":"KIRBY","gameCount":3},{"id":"0x5b1bbd","character":"DONKEY_KONG","gameCount":1},{"id":"0x62f9ab","character":"CAPTAIN_FALCON","gameCount":2}]}}},"tag":"Omenga"},"OPEM#185":{"getConnectCode":{"user":{"displayName":"InHGodWeBust","connectCode":{"code":"OPEM#185"},"rankedNetplayProfile":{"id":"0x276b66","ratingOrdinal":1847.99281,"ratingUpdateCount":51,"wins":31,"losses":20,"dailyGlobalPlacement":null,"dailyRegionalPlacement":null,"continent":"NORTH_AMERICA","characters":[{"id":"0x173e12e","character":"FOX","gameCount":111}]}}},"tag":"Trevor"},"OVAL#154":{"getConnectCode":{"user":{"displayName":"ILoveMyWife1976","connectCode":{"code":"OVAL#154"},"rankedNetplayProfile":{"id":"0x25e768","ratingOrdinal":1246.538142,"ratingUpdateCount":76,"wins":36,"losses":40,"dailyGlobalPlacement":null,"dailyRegionalPlacement":null,"continent":"NORTH_AMERICA","characters":[{"id":"0x194bbc4","character":"FOX","gameCount":136}]}}},"tag":"Oval"},"PINK#715":{"getConnectCode":{"user":{"displayName":"dz","connectCode":{"code":"PINK#715"},"rankedNetplayProfile":{"id":"0x2d29c7","ratingOrdinal":2672.55818,"ratingUpdateCount":595,"wins":473,"losses":122,"dailyGlobalPlacement":38,"dailyRegionalPlacement":34,"continent":"NORTH_AMERICA","characters":[{"id":"0x18f6ed3","character":"YOSHI","gameCount":1358}]}}},"tag":"dz"},"PLBA#990":{"getConnectCode":{"user":{"displayName":"Pleeba","connectCode":{"code":"PLBA#990"},"rankedNetplayProfile":{"id":"0x2231fd","ratingOrdinal":1844.573935,"ratingUpdateCount":232,"wins":113,"losses":119,"dailyGlobalPlacement":null,"dailyRegionalPlacement":null,"continent":"NORTH_AMERICA","characters":[{"id":"0x121ef7c","character":"SHEIK","gameCount":202},{"id":"0x121ef7d","character":"FOX","gameCount":9},{"id":"0x121ef7e","character":"MARTH","gameCount":11},{"id":"0x121ef7f","character":"FALCO","gameCount":209}]}}},"tag":""},"POBO#212":{"getConnectCode":{"user":{"displayName":"strizz","connectCode":{"code":"POBO#212"},"rankedNetplayProfile":{"id":"0x4121b6","ratingOrdinal":1339.05165,"ratingUpdateCount":178,"wins":84,"losses":94,"dailyGlobalPlacement":null,"dailyRegionalPlacement":null,"continent":"NORTH_AMERICA","characters":[{"id":"0x11065d7","character":"YOSHI","gameCount":30},{"id":"0x11065d8","character":"SHEIK","gameCount":50},{"id":"0x11065d9","character":"FALCO","gameCount":2},{"id":"0x11065da","character":"ZELDA","gameCount":1},{"id":"0x11065db","character":"MARIO","gameCount":1},{"id":"0x11065dc","character":"MARTH","gameCount":1},{"id":"0x11065dd","character":"FOX","gameCount":194},{"id":"0x11065de","character":"CAPTAIN_FALCON","gameCount":29}]}}},"tag":"Strizz"},"PROZ#0":{"getConnectCode":{"user":{"displayName":"ProZ","connectCode":{"code":"PROZ#0"},"rankedNetplayProfile":{"id":"0x24a289","ratingOrdinal":1681.087433,"ratingUpdateCount":163,"wins":86,"losses":77,"dailyGlobalPlacement":null,"dailyRegionalPlacement":null,"continent":"NORTH_AMERICA","characters":[{"id":"0x1987444","character":"CAPTAIN_FALCON","gameCount":399}]}}},"tag":""},"PSYD#339":{"getConnectCode":{"user":{"displayName":"SleepyPsyduck","connectCode":{"code":"PSYD#339"},"rankedNetplayProfile":{"id":"0x2a3810","ratingOrdinal":1070.603166,"ratingUpdateCount":97,"wins":43,"losses":54,"dailyGlobalPlacement":null,"dailyRegionalPlacement":null,"continent":"NORTH_AMERICA","characters":[{"id":"0x2a44ad","character":"FOX","gameCount":69},{"id":"0x2a4ea7","character":"JIGGLYPUFF","gameCount":17},{"id":"0x2a6f6f","character":"DONKEY_KONG","gameCount":114},{"id":"0x4e442b","character":"CAPTAIN_FALCON","gameCount":2},{"id":"0x6c4f63","character":"YOSHI","gameCount":1},{"id":"0x6c5c11","character":"MARTH","gameCount":1},{"id":"0x6c5c12","character":"SHEIK","gameCount":1},{"id":"0x6c6f28","character":"GANONDORF","gameCount":1},{"id":"0xbac479","character":"NESS","gameCount":2},{"id":"0xbc11c2","character":"FALCO","gameCount":6}]}}},"tag":"SleepyPsyduck"},"RAID#365":{"getConnectCode":{"user":{"displayName":"Raidos","connectCode":{"code":"RAID#365"},"rankedNetplayProfile":{"id":"0x1232d25","ratingOrdinal":1100,"ratingUpdateCount":0,"wins":null,"losses":null,"dailyGlobalPlacement":null,"dailyRegionalPlacement":null,"continent":null,"characters":[]}}},"tag":"Raidos"},"REMO#969":{"getConnectCode":{"user":{"displayName":"tv/ssbmRF","connectCode":{"code":"REMO#969"},"rankedNetplayProfile":{"id":"0x244a47","ratingOrdinal":2327.617001,"ratingUpdateCount":829,"wins":444,"losses":385,"dailyGlobalPlacement":null,"dailyRegionalPlacement":null,"continent":"NORTH_AMERICA","characters":[{"id":"0x1881f38","character":"LUIGI","gameCount":1779},{"id":"0x1881f39","character":"FALCO","gameCount":1}]}}},"tag":"Remolinoferoz"},"RES#777":{"getConnectCode":{"user":{"displayName":"RE$","connectCode":{"code":"RES#777"},"rankedNetplayProfile":{"id":"0x226c57","ratingOrdinal":1446.983867,"ratingUpdateCount":268,"wins":137,"losses":131,"dailyGlobalPlacement":null,"dailyRegionalPlacement":null,"continent":"NORTH_AMERICA","characters":[{"id":"0x1abda0f","character":"SHEIK","gameCount":19},{"id":"0x1abda10","character":"MARTH","gameCount":568}]}}},"tag":"RESPRiT"},"RUBZ#721":{"getConnectCode":{"user":{"displayName":"hi","connectCode":{"code":"RUBZ#721"},"rankedNetplayProfile":{"id":"0x3c341d","ratingOrdinal":2091.592206,"ratingUpdateCount":47,"wins":31,"losses":16,"dailyGlobalPlacement":null,"dailyRegionalPlacement":null,"continent":"NORTH_AMERICA","characters":[{"id":"0x1c20115","character":"PEACH","gameCount":107}]}}},"tag":""},"SATELA#0":{"getConnectCode":{"user":{"displayName":"snake oilchange","connectCode":{"code":"SATELA#0"},"rankedNetplayProfile":{"id":"0x22a504","ratingOrdinal":1043.549142,"ratingUpdateCount":152,"wins":63,"losses":89,"dailyGlobalPlacement":null,"dailyRegionalPlacement":null,"continent":"NORTH_AMERICA","characters":[{"id":"0x189de5b","character":"DR_MARIO","gameCount":29},{"id":"0x189de5c","character":"SHEIK","gameCount":190},{"id":"0x189de5d","character":"BOWSER","gameCount":4},{"id":"0x189de5e","character":"CAPTAIN_FALCON","gameCount":5},{"id":"0x189de5f","character":"MARTH","gameCount":3},{"id":"0x189de60","character":"LINK","gameCount":13},{"id":"0x189de61","character":"JIGGLYPUFF","gameCount":2},{"id":"0x189de62","character":"GAME_AND_WATCH","gameCount":1},{"id":"0x189de63","character":"PEACH","gameCount":49},{"id":"0x189de64","character":"MARIO","gameCount":5},{"id":"0x189de65","character":"FOX","gameCount":3},{"id":"0x189de66","character":"ROY","gameCount":2},{"id":"0x189de67","character":"YOSHI","gameCount":1},{"id":"0x189de68","character":"PICHU","gameCount":2},{"id":"0x189de69","character":"FALCO","gameCount":11},{"id":"0x189de6a","character":"KIRBY","gameCount":1},{"id":"0x189de6b","character":"DONKEY_KONG","gameCount":21},{"id":"0x189de6c","character":"YOUNG_LINK","gameCount":1},{"id":"0x189de6d","character":"LUIGI","gameCount":3},{"id":"0x189de6e","character":"PIKACHU","gameCount":4},{"id":"0x196aa37","character":"SAMUS","gameCount":1}]}}},"tag":"S0UTHV13W"},"SHAB#187":{"getConnectCode":{"user":{"displayName":"shabo","connectCode":{"code":"SHAB#187"},"rankedNetplayProfile":{"id":"0x227023","ratingOrdinal":2628.455939,"ratingUpdateCount":926,"wins":721,"losses":205,"dailyGlobalPlacement":53,"dailyRegionalPlacement":48,"continent":"NORTH_AMERICA","characters":[{"id":"0x1898a48","character":"FOX","gameCount":1648}]}}},"tag":"shabo"},"SKERZ#0":{"getConnectCode":{"user":{"displayName":"Skerzo","connectCode":{"code":"SKERZ#0"},"rankedNetplayProfile":{"id":"0x224b1c","ratingOrdinal":2262.470652,"ratingUpdateCount":57,"wins":43,"losses":14,"dailyGlobalPlacement":null,"dailyRegionalPlacement":null,"continent":"NORTH_AMERICA","characters":[{"id":"0x17364c7","character":"FOX","gameCount":109}]}}},"tag":""},"SKYN#976":{"getConnectCode":{"user":{"displayName":"skynative","connectCode":{"code":"SKYN#976"},"rankedNetplayProfile":{"id":"0x309db1","ratingOrdinal":1232.429133,"ratingUpdateCount":23,"wins":11,"losses":12,"dailyGlobalPlacement":null,"dailyRegionalPlacement":null,"continent":"NORTH_AMERICA","characters":[{"id":"0x19229ca","character":"GAME_AND_WATCH","gameCount":32}]}}},"tag":"skynative"},"SKYNATIVE#976":{"getConnectCode":null,"tag":"skynative"},"SLICE#0":{"getConnectCode":{"user":{"displayName":"home(o)slice","connectCode":{"code":"SLICE#0"},"rankedNetplayProfile":{"id":"0x4e2017","ratingOrdinal":1811.377696,"ratingUpdateCount":89,"wins":52,"losses":37,"dailyGlobalPlacement":null,"dailyRegionalPlacement":null,"continent":"NORTH_AMERICA","characters":[{"id":"0x16ffcde","character":"FOX","gameCount":208}]}}},"tag":"Homeslice"},"SOL#00":{"getConnectCode":{"user":{"displayName":"home(o)girl","connectCode":{"code":"SOL#00"},"rankedNetplayProfile":{"id":"0x24c112","ratingOrdinal":1823.310556,"ratingUpdateCount":40,"wins":24,"losses":16,"dailyGlobalPlacement":null,"dailyRegionalPlacement":null,"continent":"NORTH_AMERICA","characters":[{"id":"0x1255929","character":"DR_MARIO","gameCount":78}]}}},"tag":"SoulOfficer"},"SPTA#395":{"getConnectCode":{"user":{"displayName":"CODzombiesPlyer","connectCode":{"code":"SPTA#395"},"rankedNetplayProfile":{"id":"0x3a5866","ratingOrdinal":2227.143708,"ratingUpdateCount":120,"wins":75,"losses":45,"dailyGlobalPlacement":null,"dailyRegionalPlacement":null,"continent":"NORTH_AMERICA","characters":[{"id":"0x19a72d1","character":"ICE_CLIMBERS","gameCount":1},{"id":"0x19a72d2","character":"SAMUS","gameCount":269}]}}},"tag":"1985 Bears Defense"},"STAR#526":{"getConnectCode":{"user":{"displayName":"allStar","connectCode":{"code":"STAR#526"},"rankedNetplayProfile":{"id":"0x24a114","ratingOrdinal":1225.72488,"ratingUpdateCount":526,"wins":259,"losses":267,"dailyGlobalPlacement":null,"dailyRegionalPlacement":null,"continent":"NORTH_AMERICA","characters":[{"id":"0x187dbf5","character":"JIGGLYPUFF","gameCount":445},{"id":"0x187dbf6","character":"MARTH","gameCount":178},{"id":"0x187dbf7","character":"FOX","gameCount":527},{"id":"0x187dbf8","character":"SHEIK","gameCount":57}]}}},"tag":"allStar"},"STMP#857":{"getConnectCode":{"user":{"displayName":"Witch","connectCode":{"code":"STMP#857"},"rankedNetplayProfile":{"id":"0x3be1aa","ratingOrdinal":1753.954388,"ratingUpdateCount":49,"wins":25,"losses":24,"dailyGlobalPlacement":null,"dailyRegionalPlacement":null,"continent":"NORTH_AMERICA","characters":[{"id":"0x192f08e","character":"CAPTAIN_FALCON","gameCount":119}]}}},"tag":""},"SWILL#1":{"getConnectCode":{"user":{"displayName":"uair is frame 5","connectCode":{"code":"SWILL#1"},"rankedNetplayProfile":{"id":"0x24da1f","ratingOrdinal":1873.390391,"ratingUpdateCount":162,"wins":91,"losses":71,"dailyGlobalPlacement":null,"dailyRegionalPlacement":null,"continent":"NORTH_AMERICA","characters":[{"id":"0x1a1eef8","character":"DONKEY_KONG","gameCount":4},{"id":"0x1a1eef9","character":"FOX","gameCount":37},{"id":"0x1a1eefa","character":"MARTH","gameCount":33},{"id":"0x1a1eefb","character":"FALCO","gameCount":9},{"id":"0x1a1eefc","character":"SAMUS","gameCount":8},{"id":"0x1a1eefd","character":"YOUNG_LINK","gameCount":179},{"id":"0x1a1eefe","character":"CAPTAIN_FALCON","gameCount":94}]}}},"tag":"Swill_"},"SWILL#2":{"getConnectCode":{"user":{"displayName":"budlightyear","connectCode":{"code":"SWILL#2"},"rankedNetplayProfile":{"id":"0x24e237","ratingOrdinal":1767.43685,"ratingUpdateCount":203,"wins":108,"losses":95,"dailyGlobalPlacement":null,"dailyRegionalPlacement":null,"continent":"NORTH_AMERICA","characters":[{"id":"0x3240aa","character":"YOUNG_LINK","gameCount":441},{"id":"0x4ff079","character":"ROY","gameCount":9},{"id":"0x5039ec","character":"DONKEY_KONG","gameCount":4}]}}},"tag":"Swill_"},"SYN#716":{"getConnectCode":{"user":{"displayName":"wakenvape","connectCode":{"code":"SYN#716"},"rankedNetplayProfile":{"id":"0x9ae5c7","ratingOrdinal":1990.982849,"ratingUpdateCount":496,"wins":251,"losses":245,"dailyGlobalPlacement":null,"dailyRegionalPlacement":null,"continent":"NORTH_AMERICA","characters":[{"id":"0x186ba66","character":"FOX","gameCount":23},{"id":"0x186ba67","character":"GANONDORF","gameCount":5},{"id":"0x186ba68","character":"MARTH","gameCount":34},{"id":"0x186ba69","character":"SHEIK","gameCount":6},{"id":"0x186ba6a","character":"FALCO","gameCount":8},{"id":"0x186ba6b","character":"PEACH","gameCount":906},{"id":"0x186ba6c","character":"JIGGLYPUFF","gameCount":4},{"id":"0x186ba6d","character":"CAPTAIN_FALCON","gameCount":2},{"id":"0x1870f2a","character":"LINK","gameCount":2},{"id":"0x1a577de","character":"LUIGI","gameCount":1},{"id":"0x1a5b76a","character":"MARIO","gameCount":16},{"id":"0x1a62f6f","character":"DONKEY_KONG","gameCount":1}]}}},"tag":""},"TACO#383":{"getConnectCode":{"user":{"displayName":"NerdyCuber","connectCode":{"code":"TACO#383"},"rankedNetplayProfile":{"id":"0x453e0d","ratingOrdinal":1637.611793,"ratingUpdateCount":134,"wins":69,"losses":65,"dailyGlobalPlacement":null,"dailyRegionalPlacement":null,"continent":"NORTH_AMERICA","characters":[{"id":"0x1a43ba6","character":"FALCO","gameCount":252}]}}},"tag":"Nerdy"},"TAZA#0":{"getConnectCode":{"user":{"displayName":"Taza","connectCode":{"code":"TAZA#0"},"rankedNetplayProfile":{"id":"0x222b61","ratingOrdinal":2022.823369,"ratingUpdateCount":40,"wins":25,"losses":15,"dailyGlobalPlacement":null,"dailyRegionalPlacement":null,"continent":"NORTH_AMERICA","characters":[{"id":"0x18bcc0c","character":"DONKEY_KONG","gameCount":93}]}}},"tag":""},"TEN#0":{"getConnectCode":{"user":{"displayName":"t3","connectCode":{"code":"TEN#0"},"rankedNetplayProfile":{"id":"0x224408","ratingOrdinal":1330.895516,"ratingUpdateCount":602,"wins":301,"losses":301,"dailyGlobalPlacement":null,"dailyRegionalPlacement":null,"continent":"NORTH_AMERICA","characters":[{"id":"0x1873d91","character":"SHEIK","gameCount":2},{"id":"0x1873d92","character":"FALCO","gameCount":841},{"id":"0x1873d93","character":"FOX","gameCount":360},{"id":"0x1873d94","character":"MARIO","gameCount":2}]}}},"tag":"Tenacity"},"TICK#356":{"getConnectCode":{"user":{"displayName":"Tickct","connectCode":{"code":"TICK#356"},"rankedNetplayProfile":{"id":"0xb5ad0f","ratingOrdinal":1024.019366,"ratingUpdateCount":14,"wins":4,"losses":10,"dailyGlobalPlacement":null,"dailyRegionalPlacement":null,"continent":"NORTH_AMERICA","characters":[{"id":"0xb5b418","character":"MARTH","gameCount":31}]}}},"tag":"tickct"},"TPWN#485":{"getConnectCode":{"user":{"displayName":"tpwn","connectCode":{"code":"TPWN#485"},"rankedNetplayProfile":{"id":"0x267af5","ratingOrdinal":1885.486327,"ratingUpdateCount":537,"wins":272,"losses":265,"dailyGlobalPlacement":null,"dailyRegionalPlacement":null,"continent":"NORTH_AMERICA","characters":[{"id":"0x18c56a3","character":"DR_MARIO","gameCount":37},{"id":"0x18c56a4","character":"YOUNG_LINK","gameCount":1},{"id":"0x18c56a5","character":"FOX","gameCount":1},{"id":"0x18c56a6","character":"PEACH","gameCount":1160}]}}},"tag":"tpwn"},"TRAD#147":{"getConnectCode":{"user":{"displayName":"TradeWar","connectCode":{"code":"TRAD#147"},"rankedNetplayProfile":{"id":"0x24bb09","ratingOrdinal":826.756929,"ratingUpdateCount":71,"wins":23,"losses":48,"dailyGlobalPlacement":null,"dailyRegionalPlacement":null,"continent":"NORTH_AMERICA","characters":[{"id":"0x1a0b2b6","character":"MARTH","gameCount":122}]}}},"tag":"trade war"},"TUCK#214":{"getConnectCode":{"user":{"displayName":"Tuck","connectCode":{"code":"TUCK#214"},"rankedNetplayProfile":{"id":"0x24d25e","ratingOrdinal":1760.340598,"ratingUpdateCount":98,"wins":55,"losses":43,"dailyGlobalPlacement":null,"dailyRegionalPlacement":null,"continent":"NORTH_AMERICA","characters":[{"id":"0x24e700","character":"ZELDA","gameCount":230}]}}},"tag":"Tuck"},"UN#0":{"getConnectCode":{"user":{"displayName":"unsure","connectCode":{"code":"UN#0"},"rankedNetplayProfile":{"id":"0x2229c4","ratingOrdinal":2269.040655,"ratingUpdateCount":284,"wins":174,"losses":110,"dailyGlobalPlacement":null,"dailyRegionalPlacement":null,"continent":"NORTH_AMERICA","characters":[{"id":"0x197a9a0","character":"FOX","gameCount":665}]}}},"tag":"Unsure"},"UWU#696":{"getConnectCode":{"user":{"displayName":"Monikasfavpuff","connectCode":{"code":"UWU#696"},"rankedNetplayProfile":{"id":"0x240913","ratingOrdinal":1772.321141,"ratingUpdateCount":23,"wins":15,"losses":8,"dailyGlobalPlacement":null,"dailyRegionalPlacement":null,"continent":"NORTH_AMERICA","characters":[{"id":"0x28bf87","character":"JIGGLYPUFF","gameCount":50},{"id":"0x754a04","character":"FALCO","gameCount":1},{"id":"0x81e989","character":"ZELDA","gameCount":1}]}}},"tag":"Rocks"},"VINE#417":{"getConnectCode":{"user":{"displayName":"Vinegar","connectCode":{"code":"VINE#417"},"rankedNetplayProfile":{"id":"0x631127","ratingOrdinal":1612.614537,"ratingUpdateCount":190,"wins":99,"losses":91,"dailyGlobalPlacement":null,"dailyRegionalPlacement":null,"continent":"NORTH_AMERICA","characters":[{"id":"0x141e2f1","character":"FALCO","gameCount":249},{"id":"0x141e2f2","character":"FOX","gameCount":1}]}}},"tag":"Vinegar"},"WONG#420":{"getConnectCode":{"user":{"displayName":"chiliwong","connectCode":{"code":"WONG#420"},"rankedNetplayProfile":{"id":"0x252789","ratingOrdinal":1056.713198,"ratingUpdateCount":161,"wins":79,"losses":82,"dailyGlobalPlacement":null,"dailyRegionalPlacement":null,"continent":"NORTH_AMERICA","characters":[{"id":"0x192f89e","character":"LUIGI","gameCount":18},{"id":"0x192f89f","character":"ICE_CLIMBERS","gameCount":328},{"id":"0x192f8a0","character":"FOX","gameCount":1}]}}},"tag":"chiliwong"},"XXX#0":{"getConnectCode":{"user":{"displayName":"3XO","connectCode":{"code":"XXX#0"},"rankedNetplayProfile":{"id":"0x271891","ratingOrdinal":1355.928796,"ratingUpdateCount":149,"wins":72,"losses":77,"dailyGlobalPlacement":null,"dailyRegionalPlacement":null,"continent":"NORTH_AMERICA","characters":[{"id":"0x1939a4d","character":"FALCO","gameCount":286},{"id":"0x1939a4e","character":"JIGGLYPUFF","gameCount":7},{"id":"0x1939a4f","character":"MARTH","gameCount":2},{"id":"0x1939a50","character":"ROY","gameCount":1}]}}},"tag":"THR33EXOH"},"YUK#158":{"getConnectCode":{"user":{"displayName":"yuk","connectCode":{"code":"YUK#158"},"rankedNetplayProfile":{"id":"0x48f03c","ratingOrdinal":2005.516246,"ratingUpdateCount":189,"wins":105,"losses":84,"dailyGlobalPlacement":null,"dailyRegionalPlacement":null,"continent":"NORTH_AMERICA","characters":[{"id":"0x1bcd7c6","character":"JIGGLYPUFF","gameCount":1},{"id":"0x1bcd7c7","character":"SHEIK","gameCount":1},{"id":"0x1bcd7c8","character":"FOX","gameCount":371},{"id":"0x1bcd7c9","character":"MARTH","gameCount":28}]}}},"tag":"Yuk"},"ZANE#0":{"getConnectCode":{"user":{"displayName":"lame fox","connectCode":{"code":"ZANE#0"},"rankedNetplayProfile":{"id":"0x238370","ratingOrdinal":1856.251946,"ratingUpdateCount":315,"wins":162,"losses":153,"dailyGlobalPlacement":null,"dailyRegionalPlacement":null,"continent":"NORTH_AMERICA","characters":[{"id":"0x18afd72","character":"MARTH","gameCount":4},{"id":"0x18afd73","character":"SHEIK","gameCount":155},{"id":"0x18afd74","character":"FOX","gameCount":600},{"id":"0x18afd75","character":"JIGGLYPUFF","gameCount":1}]}}},"tag":"Underscore"},"ZO#639":{"getConnectCode":{"user":{"displayName":"Star","connectCode":{"code":"ZO#639"},"rankedNetplayProfile":{"id":"0x7174c0","ratingOrdinal":1560.31302,"ratingUpdateCount":17,"wins":10,"losses":7,"dailyGlobalPlacement":null,"dailyRegionalPlacement":null,"continent":"NORTH_AMERICA","characters":[{"id":"0x717d91","character":"FOX","gameCount":42}]}}},"tag":"Star"}},"updatedAt":1683117010}